{".class":"MypyFile","_fullname":"PyQt6.QtWebChannel","future_import_flags":[],"is_partial_stub_package":false,"is_stub":true,"names":{".class":"SymbolTable","PYQT_SIGNAL":{".class":"SymbolTableNode","kind":"Gdef","node":{".class":"TypeAlias","alias_tvars":[],"column":0,"fullname":"PyQt6.QtWebChannel.PYQT_SIGNAL","line":38,"no_args":false,"normalized":false,"python_3_12_type_alias":false,"target":{".class":"UnionType","items":["PyQt6.QtCore.pyqtSignal","PyQt6.QtCore.pyqtBoundSignal"],"uses_pep604_syntax":false}}},"PYQT_SLOT":{".class":"SymbolTableNode","kind":"Gdef","node":{".class":"TypeAlias","alias_tvars":[],"column":0,"fullname":"PyQt6.QtWebChannel.PYQT_SLOT","line":39,"no_args":false,"normalized":false,"python_3_12_type_alias":false,"target":{".class":"UnionType","items":[{".class":"CallableType","arg_kinds":[2,4],"arg_names":[null,null],"arg_types":[{".class":"AnyType","missing_import_name":null,"source_any":null,"type_of_any":6},{".class":"AnyType","missing_import_name":null,"source_any":null,"type_of_any":6}],"bound_args":[],"def_extras":{},"fallback":"builtins.function","from_concatenate":false,"implicit":false,"imprecise_arg_kinds":false,"is_ellipsis_args":true,"name":null,"ret_type":{".class":"AnyType","missing_import_name":null,"source_any":null,"type_of_any":6},"type_guard":null,"type_is":null,"unpack_kwargs":false,"variables":[]},"PyQt6.QtCore.pyqtBoundSignal"],"uses_pep604_syntax":false}}},"PyQt6":{".class":"SymbolTableNode","cross_ref":"PyQt6","kind":"Gdef","module_hidden":true,"module_public":false},"QWebChannel":{".class":"SymbolTableNode","kind":"Gdef","node":{".class":"TypeInfo","_promote":[],"abstract_attributes":[],"alt_promote":null,"bases":["PyQt6.QtCore.QObject"],"dataclass_transform_spec":null,"declared_metaclass":null,"defn":{".class":"ClassDef","fullname":"PyQt6.QtWebChannel.QWebChannel","name":"QWebChannel","type_vars":[]},"deletable_attributes":[],"deprecated":null,"flags":[],"fullname":"PyQt6.QtWebChannel.QWebChannel","has_param_spec_type":false,"metaclass_type":null,"metadata":{},"module_name":"PyQt6.QtWebChannel","mro":["PyQt6.QtWebChannel.QWebChannel","PyQt6.QtCore.QObject","PyQt6.sip.wrapper","PyQt6.sip.simplewrapper","builtins.object"],"names":{".class":"SymbolTable","__init__":{".class":"SymbolTableNode","kind":"Mdef","node":{".class":"FuncDef","abstract_status":0,"arg_kinds":[0,1],"arg_names":["self","parent"],"dataclass_transform_spec":null,"deprecated":null,"flags":[],"fullname":"PyQt6.QtWebChannel.QWebChannel.__init__","name":"__init__","type":{".class":"CallableType","arg_kinds":[0,1],"arg_names":["self","parent"],"arg_types":["PyQt6.QtWebChannel.QWebChannel",{".class":"UnionType","items":["PyQt6.QtCore.QObject",{".class":"NoneType"}],"uses_pep604_syntax":false}],"bound_args":[],"def_extras":{"first_arg":"self"},"fallback":"builtins.function","from_concatenate":false,"implicit":false,"imprecise_arg_kinds":false,"is_ellipsis_args":false,"name":"__init__ of QWebChannel","ret_type":{".class":"NoneType"},"type_guard":null,"type_is":null,"unpack_kwargs":false,"variables":[]}}},"blockUpdates":{".class":"SymbolTableNode","kind":"Mdef","node":{".class":"FuncDef","abstract_status":0,"arg_kinds":[0],"arg_names":["self"],"dataclass_transform_spec":null,"deprecated":null,"flags":[],"fullname":"PyQt6.QtWebChannel.QWebChannel.blockUpdates","name":"blockUpdates","type":{".class":"CallableType","arg_kinds":[0],"arg_names":["self"],"arg_types":["PyQt6.QtWebChannel.QWebChannel"],"bound_args":[],"def_extras":{"first_arg":"self"},"fallback":"builtins.function","from_concatenate":false,"implicit":false,"imprecise_arg_kinds":false,"is_ellipsis_args":false,"name":"blockUpdates of QWebChannel","ret_type":"builtins.bool","type_guard":null,"type_is":null,"unpack_kwargs":false,"variables":[]}}},"blockUpdatesChanged":{".class":"SymbolTableNode","kind":"Mdef","node":{".class":"Var","flags":["is_initialized_in_class","is_classvar","is_ready"],"fullname":"PyQt6.QtWebChannel.QWebChannel.blockUpdatesChanged","name":"blockUpdatesChanged","type":"PyQt6.QtCore.pyqtSignal"}},"connectTo":{".class":"SymbolTableNode","kind":"Mdef","node":{".class":"FuncDef","abstract_status":0,"arg_kinds":[0,0],"arg_names":["self","transport"],"dataclass_transform_spec":null,"deprecated":null,"flags":[],"fullname":"PyQt6.QtWebChannel.QWebChannel.connectTo","name":"connectTo","type":{".class":"CallableType","arg_kinds":[0,0],"arg_names":["self","transport"],"arg_types":["PyQt6.QtWebChannel.QWebChannel",{".class":"UnionType","items":["PyQt6.QtWebChannel.QWebChannelAbstractTransport",{".class":"NoneType"}],"uses_pep604_syntax":false}],"bound_args":[],"def_extras":{"first_arg":"self"},"fallback":"builtins.function","from_concatenate":false,"implicit":false,"imprecise_arg_kinds":false,"is_ellipsis_args":false,"name":"connectTo of QWebChannel","ret_type":{".class":"NoneType"},"type_guard":null,"type_is":null,"unpack_kwargs":false,"variables":[]}}},"deregisterObject":{".class":"SymbolTableNode","kind":"Mdef","node":{".class":"FuncDef","abstract_status":0,"arg_kinds":[0,0],"arg_names":["self","object"],"dataclass_transform_spec":null,"deprecated":null,"flags":[],"fullname":"PyQt6.QtWebChannel.QWebChannel.deregisterObject","name":"deregisterObject","type":{".class":"CallableType","arg_kinds":[0,0],"arg_names":["self","object"],"arg_types":["PyQt6.QtWebChannel.QWebChannel",{".class":"UnionType","items":["PyQt6.QtCore.QObject",{".class":"NoneType"}],"uses_pep604_syntax":false}],"bound_args":[],"def_extras":{"first_arg":"self"},"fallback":"builtins.function","from_concatenate":false,"implicit":false,"imprecise_arg_kinds":false,"is_ellipsis_args":false,"name":"deregisterObject of QWebChannel","ret_type":{".class":"NoneType"},"type_guard":null,"type_is":null,"unpack_kwargs":false,"variables":[]}}},"disconnectFrom":{".class":"SymbolTableNode","kind":"Mdef","node":{".class":"FuncDef","abstract_status":0,"arg_kinds":[0,0],"arg_names":["self","transport"],"dataclass_transform_spec":null,"deprecated":null,"flags":[],"fullname":"PyQt6.QtWebChannel.QWebChannel.disconnectFrom","name":"disconnectFrom","type":{".class":"CallableType","arg_kinds":[0,0],"arg_names":["self","transport"],"arg_types":["PyQt6.QtWebChannel.QWebChannel",{".class":"UnionType","items":["PyQt6.QtWebChannel.QWebChannelAbstractTransport",{".class":"NoneType"}],"uses_pep604_syntax":false}],"bound_args":[],"def_extras":{"first_arg":"self"},"fallback":"builtins.function","from_concatenate":false,"implicit":false,"imprecise_arg_kinds":false,"is_ellipsis_args":false,"name":"disconnectFrom of QWebChannel","ret_type":{".class":"NoneType"},"type_guard":null,"type_is":null,"unpack_kwargs":false,"variables":[]}}},"propertyUpdateInterval":{".class":"SymbolTableNode","kind":"Mdef","node":{".class":"FuncDef","abstract_status":0,"arg_kinds":[0],"arg_names":["self"],"dataclass_transform_spec":null,"deprecated":null,"flags":[],"fullname":"PyQt6.QtWebChannel.QWebChannel.propertyUpdateInterval","name":"propertyUpdateInterval","type":{".class":"CallableType","arg_kinds":[0],"arg_names":["self"],"arg_types":["PyQt6.QtWebChannel.QWebChannel"],"bound_args":[],"def_extras":{"first_arg":"self"},"fallback":"builtins.function","from_concatenate":false,"implicit":false,"imprecise_arg_kinds":false,"is_ellipsis_args":false,"name":"propertyUpdateInterval of QWebChannel","ret_type":"builtins.int","type_guard":null,"type_is":null,"unpack_kwargs":false,"variables":[]}}},"registerObject":{".class":"SymbolTableNode","kind":"Mdef","node":{".class":"FuncDef","abstract_status":0,"arg_kinds":[0,0,0],"arg_names":["self","id","object"],"dataclass_transform_spec":null,"deprecated":null,"flags":[],"fullname":"PyQt6.QtWebChannel.QWebChannel.registerObject","name":"registerObject","type":{".class":"CallableType","arg_kinds":[0,0,0],"arg_names":["self","id","object"],"arg_types":["PyQt6.QtWebChannel.QWebChannel",{".class":"UnionType","items":["builtins.str",{".class":"NoneType"}],"uses_pep604_syntax":false},{".class":"UnionType","items":["PyQt6.QtCore.QObject",{".class":"NoneType"}],"uses_pep604_syntax":false}],"bound_args":[],"def_extras":{"first_arg":"self"},"fallback":"builtins.function","from_concatenate":false,"implicit":false,"imprecise_arg_kinds":false,"is_ellipsis_args":false,"name":"registerObject of QWebChannel","ret_type":{".class":"NoneType"},"type_guard":null,"type_is":null,"unpack_kwargs":false,"variables":[]}}},"registerObjects":{".class":"SymbolTableNode","kind":"Mdef","node":{".class":"FuncDef","abstract_status":0,"arg_kinds":[0,0],"arg_names":["self","objects"],"dataclass_transform_spec":null,"deprecated":null,"flags":[],"fullname":"PyQt6.QtWebChannel.QWebChannel.registerObjects","name":"registerObjects","type":{".class":"CallableType","arg_kinds":[0,0],"arg_names":["self","objects"],"arg_types":["PyQt6.QtWebChannel.QWebChannel",{".class":"Instance","args":[{".class":"UnionType","items":["builtins.str",{".class":"NoneType"}],"uses_pep604_syntax":false},"PyQt6.QtCore.QObject"],"extra_attrs":null,"type_ref":"builtins.dict"}],"bound_args":[],"def_extras":{"first_arg":"self"},"fallback":"builtins.function","from_concatenate":false,"implicit":false,"imprecise_arg_kinds":false,"is_ellipsis_args":false,"name":"registerObjects of QWebChannel","ret_type":{".class":"NoneType"},"type_guard":null,"type_is":null,"unpack_kwargs":false,"variables":[]}}},"registeredObjects":{".class":"SymbolTableNode","kind":"Mdef","node":{".class":"FuncDef","abstract_status":0,"arg_kinds":[0],"arg_names":["self"],"dataclass_transform_spec":null,"deprecated":null,"flags":[],"fullname":"PyQt6.QtWebChannel.QWebChannel.registeredObjects","name":"registeredObjects","type":{".class":"CallableType","arg_kinds":[0],"arg_names":["self"],"arg_types":["PyQt6.QtWebChannel.QWebChannel"],"bound_args":[],"def_extras":{"first_arg":"self"},"fallback":"builtins.function","from_concatenate":false,"implicit":false,"imprecise_arg_kinds":false,"is_ellipsis_args":false,"name":"registeredObjects of QWebChannel","ret_type":{".class":"Instance","args":["builtins.str","PyQt6.QtCore.QObject"],"extra_attrs":null,"type_ref":"builtins.dict"},"type_guard":null,"type_is":null,"unpack_kwargs":false,"variables":[]}}},"setBlockUpdates":{".class":"SymbolTableNode","kind":"Mdef","node":{".class":"FuncDef","abstract_status":0,"arg_kinds":[0,0],"arg_names":["self","block"],"dataclass_transform_spec":null,"deprecated":null,"flags":[],"fullname":"PyQt6.QtWebChannel.QWebChannel.setBlockUpdates","name":"setBlockUpdates","type":{".class":"CallableType","arg_kinds":[0,0],"arg_names":["self","block"],"arg_types":["PyQt6.QtWebChannel.QWebChannel","builtins.bool"],"bound_args":[],"def_extras":{"first_arg":"self"},"fallback":"builtins.function","from_concatenate":false,"implicit":false,"imprecise_arg_kinds":false,"is_ellipsis_args":false,"name":"setBlockUpdates of QWebChannel","ret_type":{".class":"NoneType"},"type_guard":null,"type_is":null,"unpack_kwargs":false,"variables":[]}}},"setPropertyUpdateInterval":{".class":"SymbolTableNode","kind":"Mdef","node":{".class":"FuncDef","abstract_status":0,"arg_kinds":[0,0],"arg_names":["self","ms"],"dataclass_transform_spec":null,"deprecated":null,"flags":[],"fullname":"PyQt6.QtWebChannel.QWebChannel.setPropertyUpdateInterval","name":"setPropertyUpdateInterval","type":{".class":"CallableType","arg_kinds":[0,0],"arg_names":["self","ms"],"arg_types":["PyQt6.QtWebChannel.QWebChannel","builtins.int"],"bound_args":[],"def_extras":{"first_arg":"self"},"fallback":"builtins.function","from_concatenate":false,"implicit":false,"imprecise_arg_kinds":false,"is_ellipsis_args":false,"name":"setPropertyUpdateInterval of QWebChannel","ret_type":{".class":"NoneType"},"type_guard":null,"type_is":null,"unpack_kwargs":false,"variables":[]}}}},"self_type":{".class":"TypeVarType","default":{".class":"AnyType","missing_import_name":null,"source_any":null,"type_of_any":4},"fullname":"PyQt6.QtWebChannel.QWebChannel.Self","id":0,"name":"Self","namespace":"","upper_bound":"PyQt6.QtWebChannel.QWebChannel","values":[],"variance":0},"slots":null,"tuple_type":null,"type_vars":[],"typeddict_type":null}},"QWebChannelAbstractTransport":{".class":"SymbolTableNode","kind":"Gdef","node":{".class":"TypeInfo","_promote":[],"abstract_attributes":[],"alt_promote":null,"bases":["PyQt6.QtCore.QObject"],"dataclass_transform_spec":null,"declared_metaclass":null,"defn":{".class":"ClassDef","fullname":"PyQt6.QtWebChannel.QWebChannelAbstractTransport","name":"QWebChannelAbstractTransport","type_vars":[]},"deletable_attributes":[],"deprecated":null,"flags":[],"fullname":"PyQt6.QtWebChannel.QWebChannelAbstractTransport","has_param_spec_type":false,"metaclass_type":null,"metadata":{},"module_name":"PyQt6.QtWebChannel","mro":["PyQt6.QtWebChannel.QWebChannelAbstractTransport","PyQt6.QtCore.QObject","PyQt6.sip.wrapper","PyQt6.sip.simplewrapper","builtins.object"],"names":{".class":"SymbolTable","__init__":{".class":"SymbolTableNode","kind":"Mdef","node":{".class":"FuncDef","abstract_status":0,"arg_kinds":[0,1],"arg_names":["self","parent"],"dataclass_transform_spec":null,"deprecated":null,"flags":[],"fullname":"PyQt6.QtWebChannel.QWebChannelAbstractTransport.__init__","name":"__init__","type":{".class":"CallableType","arg_kinds":[0,1],"arg_names":["self","parent"],"arg_types":["PyQt6.QtWebChannel.QWebChannelAbstractTransport",{".class":"UnionType","items":["PyQt6.QtCore.QObject",{".class":"NoneType"}],"uses_pep604_syntax":false}],"bound_args":[],"def_extras":{"first_arg":"self"},"fallback":"builtins.function","from_concatenate":false,"implicit":false,"imprecise_arg_kinds":false,"is_ellipsis_args":false,"name":"__init__ of QWebChannelAbstractTransport","ret_type":{".class":"NoneType"},"type_guard":null,"type_is":null,"unpack_kwargs":false,"variables":[]}}},"messageReceived":{".class":"SymbolTableNode","kind":"Mdef","node":{".class":"Var","flags":["is_initialized_in_class","is_classvar","is_ready"],"fullname":"PyQt6.QtWebChannel.QWebChannelAbstractTransport.messageReceived","name":"messageReceived","type":"PyQt6.QtCore.pyqtSignal"}},"sendMessage":{".class":"SymbolTableNode","kind":"Mdef","node":{".class":"FuncDef","abstract_status":0,"arg_kinds":[0,0],"arg_names":["self","message"],"dataclass_transform_spec":null,"deprecated":null,"flags":[],"fullname":"PyQt6.QtWebChannel.QWebChannelAbstractTransport.sendMessage","name":"sendMessage","type":{".class":"CallableType","arg_kinds":[0,0],"arg_names":["self","message"],"arg_types":["PyQt6.QtWebChannel.QWebChannelAbstractTransport",{".class":"Instance","args":[{".class":"UnionType","items":["builtins.str",{".class":"NoneType"}],"uses_pep604_syntax":false},{".class":"UnionType","items":["PyQt6.QtCore.QJsonValue","PyQt6.QtCore.QJsonValue.Type",{".class":"Instance","args":["PyQt6.QtCore.QJsonValue"],"extra_attrs":null,"type_ref":"typing.Iterable"},{".class":"Instance","args":[{".class":"UnionType","items":["builtins.str",{".class":"NoneType"}],"uses_pep604_syntax":false},"PyQt6.QtCore.QJsonValue"],"extra_attrs":null,"type_ref":"builtins.dict"},"builtins.bool","builtins.int","builtins.float",{".class":"NoneType"},"builtins.str",{".class":"NoneType"}],"uses_pep604_syntax":false}],"extra_attrs":null,"type_ref":"builtins.dict"}],"bound_args":[],"def_extras":{"first_arg":"self"},"fallback":"builtins.function","from_concatenate":false,"implicit":false,"imprecise_arg_kinds":false,"is_ellipsis_args":false,"name":"sendMessage of QWebChannelAbstractTransport","ret_type":{".class":"NoneType"},"type_guard":null,"type_is":null,"unpack_kwargs":false,"variables":[]}}}},"self_type":{".class":"TypeVarType","default":{".class":"AnyType","missing_import_name":null,"source_any":null,"type_of_any":4},"fullname":"PyQt6.QtWebChannel.QWebChannelAbstractTransport.Self","id":0,"name":"Self","namespace":"","upper_bound":"PyQt6.QtWebChannel.QWebChannelAbstractTransport","values":[],"variance":0},"slots":null,"tuple_type":null,"type_vars":[],"typeddict_type":null}},"QtCore":{".class":"SymbolTableNode","cross_ref":"PyQt6.QtCore","kind":"Gdef","module_hidden":true,"module_public":false},"__annotations__":{".class":"SymbolTableNode","kind":"Gdef","node":{".class":"Var","flags":["is_ready"],"fullname":"PyQt6.QtWebChannel.__annotations__","name":"__annotations__","type":{".class":"Instance","args":["builtins.str",{".class":"AnyType","missing_import_name":null,"source_any":null,"type_of_any":6}],"extra_attrs":null,"type_ref":"builtins.dict"}}},"__doc__":{".class":"SymbolTableNode","kind":"Gdef","node":{".class":"Var","flags":["is_ready"],"fullname":"PyQt6.QtWebChannel.__doc__","name":"__doc__","type":"builtins.str"}},"__file__":{".class":"SymbolTableNode","kind":"Gdef","node":{".class":"Var","flags":["is_ready"],"fullname":"PyQt6.QtWebChannel.__file__","name":"__file__","type":"builtins.str"}},"__name__":{".class":"SymbolTableNode","kind":"Gdef","node":{".class":"Var","flags":["is_ready"],"fullname":"PyQt6.QtWebChannel.__name__","name":"__name__","type":"builtins.str"}},"__package__":{".class":"SymbolTableNode","kind":"Gdef","node":{".class":"Var","flags":["is_ready"],"fullname":"PyQt6.QtWebChannel.__package__","name":"__package__","type":"builtins.str"}},"__spec__":{".class":"SymbolTableNode","kind":"Gdef","node":{".class":"Var","flags":["is_ready"],"fullname":"PyQt6.QtWebChannel.__spec__","name":"__spec__","type":"_frozen_importlib.ModuleSpec"}},"collections":{".class":"SymbolTableNode","cross_ref":"collections","kind":"Gdef","module_hidden":true,"module_public":false},"datetime":{".class":"SymbolTableNode","cross_ref":"datetime","kind":"Gdef","module_hidden":true,"module_public":false},"deprecated":{".class":"SymbolTableNode","cross_ref":"warnings.deprecated","kind":"Gdef","module_hidden":true,"module_public":false},"re":{".class":"SymbolTableNode","cross_ref":"re","kind":"Gdef","module_hidden":true,"module_public":false},"typing":{".class":"SymbolTableNode","cross_ref":"typing","kind":"Gdef","module_hidden":true,"module_public":false}},"path":"/Users/likai/Github/Tools/Anki-addon-dev-toolkit/.venv/lib/python3.13/site-packages/PyQt6/QtWebChannel.pyi"}