{".class":"MypyFile","_fullname":"questionary.prompts.press_any_key_to_continue","future_import_flags":[],"is_partial_stub_package":false,"is_stub":false,"names":{".class":"SymbolTable","Any":{".class":"SymbolTableNode","cross_ref":"typing.Any","kind":"Gdef"},"KeyBindings":{".class":"SymbolTableNode","cross_ref":"prompt_toolkit.key_binding.key_bindings.KeyBindings","kind":"Gdef"},"Keys":{".class":"SymbolTableNode","cross_ref":"prompt_toolkit.keys.Keys","kind":"Gdef"},"Optional":{".class":"SymbolTableNode","cross_ref":"typing.Optional","kind":"Gdef"},"PromptSession":{".class":"SymbolTableNode","cross_ref":"prompt_toolkit.shortcuts.prompt.PromptSession","kind":"Gdef"},"Question":{".class":"SymbolTableNode","cross_ref":"questionary.question.Question","kind":"Gdef"},"Style":{".class":"SymbolTableNode","cross_ref":"prompt_toolkit.styles.style.Style","kind":"Gdef"},"__annotations__":{".class":"SymbolTableNode","kind":"Gdef","node":{".class":"Var","flags":["is_ready"],"fullname":"questionary.prompts.press_any_key_to_continue.__annotations__","name":"__annotations__","type":{".class":"Instance","args":["builtins.str",{".class":"AnyType","missing_import_name":null,"source_any":null,"type_of_any":6}],"extra_attrs":null,"type_ref":"builtins.dict"}}},"__doc__":{".class":"SymbolTableNode","kind":"Gdef","node":{".class":"Var","flags":["is_ready"],"fullname":"questionary.prompts.press_any_key_to_continue.__doc__","name":"__doc__","type":"builtins.str"}},"__file__":{".class":"SymbolTableNode","kind":"Gdef","node":{".class":"Var","flags":["is_ready"],"fullname":"questionary.prompts.press_any_key_to_continue.__file__","name":"__file__","type":"builtins.str"}},"__name__":{".class":"SymbolTableNode","kind":"Gdef","node":{".class":"Var","flags":["is_ready"],"fullname":"questionary.prompts.press_any_key_to_continue.__name__","name":"__name__","type":"builtins.str"}},"__package__":{".class":"SymbolTableNode","kind":"Gdef","node":{".class":"Var","flags":["is_ready"],"fullname":"questionary.prompts.press_any_key_to_continue.__package__","name":"__package__","type":"builtins.str"}},"__spec__":{".class":"SymbolTableNode","kind":"Gdef","node":{".class":"Var","flags":["is_ready"],"fullname":"questionary.prompts.press_any_key_to_continue.__spec__","name":"__spec__","type":"_frozen_importlib.ModuleSpec"}},"merge_styles_default":{".class":"SymbolTableNode","cross_ref":"questionary.styles.merge_styles_default","kind":"Gdef"},"press_any_key_to_continue":{".class":"SymbolTableNode","kind":"Gdef","node":{".class":"FuncDef","abstract_status":0,"arg_kinds":[1,1,4],"arg_names":["message","style","kwargs"],"dataclass_transform_spec":null,"deprecated":null,"flags":[],"fullname":"questionary.prompts.press_any_key_to_continue.press_any_key_to_continue","name":"press_any_key_to_continue","type":{".class":"CallableType","arg_kinds":[1,1,4],"arg_names":["message","style","kwargs"],"arg_types":[{".class":"UnionType","items":["builtins.str",{".class":"NoneType"}],"uses_pep604_syntax":false},{".class":"UnionType","items":["prompt_toolkit.styles.style.Style",{".class":"NoneType"}],"uses_pep604_syntax":false},{".class":"AnyType","missing_import_name":null,"source_any":null,"type_of_any":2}],"bound_args":[],"def_extras":{"first_arg":null},"fallback":"builtins.function","from_concatenate":false,"implicit":false,"imprecise_arg_kinds":false,"is_ellipsis_args":false,"name":"press_any_key_to_continue","ret_type":{".class":"AnyType","missing_import_name":null,"source_any":null,"type_of_any":1},"type_guard":null,"type_is":null,"unpack_kwargs":false,"variables":[]}}},"to_formatted_text":{".class":"SymbolTableNode","cross_ref":"prompt_toolkit.formatted_text.base.to_formatted_text","kind":"Gdef"}},"path":"/Users/likai/Github/Tools/Anki-addon-builder/.venv/lib/python3.12/site-packages/questionary/prompts/press_any_key_to_continue.py"}