{".class":"MypyFile","_fullname":"anki.foreign_data.mnemosyne","future_import_flags":[],"is_partial_stub_package":false,"is_stub":false,"names":{".class":"SymbolTable","ABC":{".class":"SymbolTableNode","cross_ref":"abc.ABC","kind":"Gdef"},"Cloze":{".class":"SymbolTableNode","kind":"Gdef","node":{".class":"TypeInfo","_promote":[],"abstract_attributes":[],"alt_promote":null,"bases":["anki.foreign_data.mnemosyne.MnemoFactView"],"dataclass_transform_spec":null,"declared_metaclass":null,"defn":{".class":"ClassDef","fullname":"anki.foreign_data.mnemosyne.Cloze","name":"Cloze","type_vars":[]},"deletable_attributes":[],"deprecated":null,"flags":[],"fullname":"anki.foreign_data.mnemosyne.Cloze","has_param_spec_type":false,"metaclass_type":"abc.ABCMeta","metadata":{},"module_name":"anki.foreign_data.mnemosyne","mro":["anki.foreign_data.mnemosyne.Cloze","anki.foreign_data.mnemosyne.MnemoFactView","abc.ABC","builtins.object"],"names":{".class":"SymbolTable","field_keys":{".class":"SymbolTableNode","kind":"Mdef","node":{".class":"Var","flags":["is_initialized_in_class","is_inferred","has_explicit_value"],"fullname":"anki.foreign_data.mnemosyne.Cloze.field_keys","name":"field_keys","type":{".class":"TupleType","implicit":false,"items":["builtins.str"],"partial_fallback":{".class":"Instance","args":[{".class":"AnyType","missing_import_name":null,"source_any":null,"type_of_any":6}],"extra_attrs":null,"type_ref":"builtins.tuple"}}}},"foreign_notetype":{".class":"SymbolTableNode","kind":"Mdef","node":{".class":"Decorator","func":{".class":"FuncDef","abstract_status":0,"arg_kinds":[0],"arg_names":["cls"],"dataclass_transform_spec":null,"deprecated":null,"flags":["is_class","is_decorated"],"fullname":"anki.foreign_data.mnemosyne.Cloze.foreign_notetype","name":"foreign_notetype","type":{".class":"CallableType","arg_kinds":[0],"arg_names":["cls"],"arg_types":[{".class":"TypeType","item":"anki.foreign_data.mnemosyne.Cloze"}],"bound_args":[],"def_extras":{"first_arg":"cls"},"fallback":"builtins.function","from_concatenate":false,"implicit":false,"imprecise_arg_kinds":false,"is_ellipsis_args":false,"name":"foreign_notetype of Cloze","ret_type":"anki.foreign_data.ForeignNotetype","type_guard":null,"type_is":null,"unpack_kwargs":false,"variables":[]}},"is_overload":false,"var":{".class":"Var","flags":["is_initialized_in_class","is_classmethod","is_ready","is_inferred"],"fullname":"anki.foreign_data.mnemosyne.Cloze.foreign_notetype","name":"foreign_notetype","type":{".class":"CallableType","arg_kinds":[0],"arg_names":["cls"],"arg_types":[{".class":"TypeType","item":"anki.foreign_data.mnemosyne.Cloze"}],"bound_args":[],"def_extras":{"first_arg":"cls"},"fallback":"builtins.function","from_concatenate":false,"implicit":false,"imprecise_arg_kinds":false,"is_ellipsis_args":false,"name":"foreign_notetype of Cloze","ret_type":"anki.foreign_data.ForeignNotetype","type_guard":null,"type_is":null,"unpack_kwargs":false,"variables":[]}}}},"notetype":{".class":"SymbolTableNode","kind":"Mdef","node":{".class":"Var","flags":["is_initialized_in_class","is_inferred","has_explicit_value"],"fullname":"anki.foreign_data.mnemosyne.Cloze.notetype","name":"notetype","type":"builtins.str"}}},"self_type":{".class":"TypeVarType","default":{".class":"AnyType","missing_import_name":null,"source_any":null,"type_of_any":4},"fullname":"anki.foreign_data.mnemosyne.Cloze.Self","id":0,"name":"Self","namespace":"","upper_bound":"anki.foreign_data.mnemosyne.Cloze","values":[],"variance":0},"slots":null,"tuple_type":null,"type_vars":[],"typeddict_type":null}},"DB":{".class":"SymbolTableNode","cross_ref":"anki.db.DB","kind":"Gdef"},"DeckId":{".class":"SymbolTableNode","cross_ref":"anki.decks.DeckId","kind":"Gdef"},"ForeignCard":{".class":"SymbolTableNode","cross_ref":"anki.foreign_data.ForeignCard","kind":"Gdef"},"ForeignCardType":{".class":"SymbolTableNode","cross_ref":"anki.foreign_data.ForeignCardType","kind":"Gdef"},"ForeignData":{".class":"SymbolTableNode","cross_ref":"anki.foreign_data.ForeignData","kind":"Gdef"},"ForeignNote":{".class":"SymbolTableNode","cross_ref":"anki.foreign_data.ForeignNote","kind":"Gdef"},"ForeignNotetype":{".class":"SymbolTableNode","cross_ref":"anki.foreign_data.ForeignNotetype","kind":"Gdef"},"FrontBack":{".class":"SymbolTableNode","kind":"Gdef","node":{".class":"TypeInfo","_promote":[],"abstract_attributes":[],"alt_promote":null,"bases":["anki.foreign_data.mnemosyne.MnemoFactView"],"dataclass_transform_spec":null,"declared_metaclass":null,"defn":{".class":"ClassDef","fullname":"anki.foreign_data.mnemosyne.FrontBack","name":"FrontBack","type_vars":[]},"deletable_attributes":[],"deprecated":null,"flags":[],"fullname":"anki.foreign_data.mnemosyne.FrontBack","has_param_spec_type":false,"metaclass_type":"abc.ABCMeta","metadata":{},"module_name":"anki.foreign_data.mnemosyne","mro":["anki.foreign_data.mnemosyne.FrontBack","anki.foreign_data.mnemosyne.MnemoFactView","abc.ABC","builtins.object"],"names":{".class":"SymbolTable","field_keys":{".class":"SymbolTableNode","kind":"Mdef","node":{".class":"Var","flags":["is_initialized_in_class","is_inferred","has_explicit_value"],"fullname":"anki.foreign_data.mnemosyne.FrontBack.field_keys","name":"field_keys","type":{".class":"TupleType","implicit":false,"items":["builtins.str","builtins.str"],"partial_fallback":{".class":"Instance","args":[{".class":"AnyType","missing_import_name":null,"source_any":null,"type_of_any":6}],"extra_attrs":null,"type_ref":"builtins.tuple"}}}},"foreign_notetype":{".class":"SymbolTableNode","kind":"Mdef","node":{".class":"Decorator","func":{".class":"FuncDef","abstract_status":0,"arg_kinds":[0],"arg_names":["cls"],"dataclass_transform_spec":null,"deprecated":null,"flags":["is_class","is_decorated"],"fullname":"anki.foreign_data.mnemosyne.FrontBack.foreign_notetype","name":"foreign_notetype","type":{".class":"CallableType","arg_kinds":[0],"arg_names":["cls"],"arg_types":[{".class":"TypeType","item":"anki.foreign_data.mnemosyne.FrontBack"}],"bound_args":[],"def_extras":{"first_arg":"cls"},"fallback":"builtins.function","from_concatenate":false,"implicit":false,"imprecise_arg_kinds":false,"is_ellipsis_args":false,"name":"foreign_notetype of FrontBack","ret_type":"anki.foreign_data.ForeignNotetype","type_guard":null,"type_is":null,"unpack_kwargs":false,"variables":[]}},"is_overload":false,"var":{".class":"Var","flags":["is_initialized_in_class","is_classmethod","is_ready","is_inferred"],"fullname":"anki.foreign_data.mnemosyne.FrontBack.foreign_notetype","name":"foreign_notetype","type":{".class":"CallableType","arg_kinds":[0],"arg_names":["cls"],"arg_types":[{".class":"TypeType","item":"anki.foreign_data.mnemosyne.FrontBack"}],"bound_args":[],"def_extras":{"first_arg":"cls"},"fallback":"builtins.function","from_concatenate":false,"implicit":false,"imprecise_arg_kinds":false,"is_ellipsis_args":false,"name":"foreign_notetype of FrontBack","ret_type":"anki.foreign_data.ForeignNotetype","type_guard":null,"type_is":null,"unpack_kwargs":false,"variables":[]}}}},"notetype":{".class":"SymbolTableNode","kind":"Mdef","node":{".class":"Var","flags":["is_initialized_in_class","is_inferred","has_explicit_value"],"fullname":"anki.foreign_data.mnemosyne.FrontBack.notetype","name":"notetype","type":"builtins.str"}}},"self_type":{".class":"TypeVarType","default":{".class":"AnyType","missing_import_name":null,"source_any":null,"type_of_any":4},"fullname":"anki.foreign_data.mnemosyne.FrontBack.Self","id":0,"name":"Self","namespace":"","upper_bound":"anki.foreign_data.mnemosyne.FrontBack","values":[],"variance":0},"slots":null,"tuple_type":null,"type_vars":[],"typeddict_type":null}},"FrontOnly":{".class":"SymbolTableNode","kind":"Gdef","node":{".class":"TypeInfo","_promote":[],"abstract_attributes":[],"alt_promote":null,"bases":["anki.foreign_data.mnemosyne.MnemoFactView"],"dataclass_transform_spec":null,"declared_metaclass":null,"defn":{".class":"ClassDef","fullname":"anki.foreign_data.mnemosyne.FrontOnly","name":"FrontOnly","type_vars":[]},"deletable_attributes":[],"deprecated":null,"flags":[],"fullname":"anki.foreign_data.mnemosyne.FrontOnly","has_param_spec_type":false,"metaclass_type":"abc.ABCMeta","metadata":{},"module_name":"anki.foreign_data.mnemosyne","mro":["anki.foreign_data.mnemosyne.FrontOnly","anki.foreign_data.mnemosyne.MnemoFactView","abc.ABC","builtins.object"],"names":{".class":"SymbolTable","field_keys":{".class":"SymbolTableNode","kind":"Mdef","node":{".class":"Var","flags":["is_initialized_in_class","is_inferred","has_explicit_value"],"fullname":"anki.foreign_data.mnemosyne.FrontOnly.field_keys","name":"field_keys","type":{".class":"TupleType","implicit":false,"items":["builtins.str","builtins.str"],"partial_fallback":{".class":"Instance","args":[{".class":"AnyType","missing_import_name":null,"source_any":null,"type_of_any":6}],"extra_attrs":null,"type_ref":"builtins.tuple"}}}},"foreign_notetype":{".class":"SymbolTableNode","kind":"Mdef","node":{".class":"Decorator","func":{".class":"FuncDef","abstract_status":0,"arg_kinds":[0],"arg_names":["cls"],"dataclass_transform_spec":null,"deprecated":null,"flags":["is_class","is_decorated"],"fullname":"anki.foreign_data.mnemosyne.FrontOnly.foreign_notetype","name":"foreign_notetype","type":{".class":"CallableType","arg_kinds":[0],"arg_names":["cls"],"arg_types":[{".class":"TypeType","item":"anki.foreign_data.mnemosyne.FrontOnly"}],"bound_args":[],"def_extras":{"first_arg":"cls"},"fallback":"builtins.function","from_concatenate":false,"implicit":false,"imprecise_arg_kinds":false,"is_ellipsis_args":false,"name":"foreign_notetype of FrontOnly","ret_type":"anki.foreign_data.ForeignNotetype","type_guard":null,"type_is":null,"unpack_kwargs":false,"variables":[]}},"is_overload":false,"var":{".class":"Var","flags":["is_initialized_in_class","is_classmethod","is_ready","is_inferred"],"fullname":"anki.foreign_data.mnemosyne.FrontOnly.foreign_notetype","name":"foreign_notetype","type":{".class":"CallableType","arg_kinds":[0],"arg_names":["cls"],"arg_types":[{".class":"TypeType","item":"anki.foreign_data.mnemosyne.FrontOnly"}],"bound_args":[],"def_extras":{"first_arg":"cls"},"fallback":"builtins.function","from_concatenate":false,"implicit":false,"imprecise_arg_kinds":false,"is_ellipsis_args":false,"name":"foreign_notetype of FrontOnly","ret_type":"anki.foreign_data.ForeignNotetype","type_guard":null,"type_is":null,"unpack_kwargs":false,"variables":[]}}}},"notetype":{".class":"SymbolTableNode","kind":"Mdef","node":{".class":"Var","flags":["is_initialized_in_class","is_inferred","has_explicit_value"],"fullname":"anki.foreign_data.mnemosyne.FrontOnly.notetype","name":"notetype","type":"builtins.str"}}},"self_type":{".class":"TypeVarType","default":{".class":"AnyType","missing_import_name":null,"source_any":null,"type_of_any":4},"fullname":"anki.foreign_data.mnemosyne.FrontOnly.Self","id":0,"name":"Self","namespace":"","upper_bound":"anki.foreign_data.mnemosyne.FrontOnly","values":[],"variance":0},"slots":null,"tuple_type":null,"type_vars":[],"typeddict_type":null}},"MnemoCard":{".class":"SymbolTableNode","kind":"Gdef","node":{".class":"TypeInfo","_promote":[],"abstract_attributes":[],"alt_promote":null,"bases":["builtins.object"],"dataclass_transform_spec":null,"declared_metaclass":null,"defn":{".class":"ClassDef","fullname":"anki.foreign_data.mnemosyne.MnemoCard","name":"MnemoCard","type_vars":[]},"deletable_attributes":[],"deprecated":null,"flags":[],"fullname":"anki.foreign_data.mnemosyne.MnemoCard","has_param_spec_type":false,"metaclass_type":null,"metadata":{"dataclass":{"attributes":[{"alias":null,"column":4,"has_default":false,"is_in_init":true,"is_init_var":false,"is_neither_frozen_nor_nonfrozen":false,"kw_only":false,"line":124,"name":"fact_view_id","type":"builtins.str"},{"alias":null,"column":4,"has_default":false,"is_in_init":true,"is_init_var":false,"is_neither_frozen_nor_nonfrozen":false,"kw_only":false,"line":125,"name":"tags","type":"builtins.str"},{"alias":null,"column":4,"has_default":false,"is_in_init":true,"is_init_var":false,"is_neither_frozen_nor_nonfrozen":false,"kw_only":false,"line":126,"name":"next_rep","type":"builtins.int"},{"alias":null,"column":4,"has_default":false,"is_in_init":true,"is_init_var":false,"is_neither_frozen_nor_nonfrozen":false,"kw_only":false,"line":127,"name":"last_rep","type":"builtins.int"},{"alias":null,"column":4,"has_default":false,"is_in_init":true,"is_init_var":false,"is_neither_frozen_nor_nonfrozen":false,"kw_only":false,"line":128,"name":"easiness","type":"builtins.float"},{"alias":null,"column":4,"has_default":false,"is_in_init":true,"is_init_var":false,"is_neither_frozen_nor_nonfrozen":false,"kw_only":false,"line":129,"name":"reps","type":"builtins.int"},{"alias":null,"column":4,"has_default":false,"is_in_init":true,"is_init_var":false,"is_neither_frozen_nor_nonfrozen":false,"kw_only":false,"line":130,"name":"lapses","type":"builtins.int"}],"frozen":false},"dataclass_tag":{}},"module_name":"anki.foreign_data.mnemosyne","mro":["anki.foreign_data.mnemosyne.MnemoCard","builtins.object"],"names":{".class":"SymbolTable","__dataclass_fields__":{".class":"SymbolTableNode","kind":"Mdef","node":{".class":"Var","flags":["is_classvar","is_ready"],"fullname":"anki.foreign_data.mnemosyne.MnemoCard.__dataclass_fields__","name":"__dataclass_fields__","type":{".class":"Instance","args":["builtins.str",{".class":"Instance","args":[{".class":"AnyType","missing_import_name":null,"source_any":null,"type_of_any":2}],"extra_attrs":null,"type_ref":"dataclasses.Field"}],"extra_attrs":null,"type_ref":"builtins.dict"}},"plugin_generated":true},"__init__":{".class":"SymbolTableNode","kind":"Mdef","node":{".class":"FuncDef","abstract_status":0,"arg_kinds":[0,0,0,0,0,0,0,0],"arg_names":["self","fact_view_id","tags","next_rep","last_rep","easiness","reps","lapses"],"dataclass_transform_spec":null,"deprecated":null,"flags":[],"fullname":"anki.foreign_data.mnemosyne.MnemoCard.__init__","name":"__init__","type":{".class":"CallableType","arg_kinds":[0,0,0,0,0,0,0,0],"arg_names":["self","fact_view_id","tags","next_rep","last_rep","easiness","reps","lapses"],"arg_types":["anki.foreign_data.mnemosyne.MnemoCard","builtins.str","builtins.str","builtins.int","builtins.int","builtins.float","builtins.int","builtins.int"],"bound_args":[],"def_extras":{},"fallback":"builtins.function","from_concatenate":false,"implicit":false,"imprecise_arg_kinds":false,"is_ellipsis_args":false,"name":"__init__ of MnemoCard","ret_type":{".class":"NoneType"},"type_guard":null,"type_is":null,"unpack_kwargs":false,"variables":[]}},"plugin_generated":true},"__match_args__":{".class":"SymbolTableNode","kind":"Mdef","node":{".class":"Var","flags":["is_ready","allow_incompatible_override"],"fullname":"anki.foreign_data.mnemosyne.MnemoCard.__match_args__","name":"__match_args__","type":{".class":"TupleType","implicit":false,"items":[{".class":"LiteralType","fallback":"builtins.str","value":"fact_view_id"},{".class":"LiteralType","fallback":"builtins.str","value":"tags"},{".class":"LiteralType","fallback":"builtins.str","value":"next_rep"},{".class":"LiteralType","fallback":"builtins.str","value":"last_rep"},{".class":"LiteralType","fallback":"builtins.str","value":"easiness"},{".class":"LiteralType","fallback":"builtins.str","value":"reps"},{".class":"LiteralType","fallback":"builtins.str","value":"lapses"}],"partial_fallback":{".class":"Instance","args":[{".class":"AnyType","missing_import_name":null,"source_any":null,"type_of_any":6}],"extra_attrs":null,"type_ref":"builtins.tuple"}}},"plugin_generated":true},"__mypy-replace":{".class":"SymbolTableNode","kind":"Mdef","node":{".class":"Decorator","func":{".class":"FuncDef","abstract_status":0,"arg_kinds":[5,5,5,5,5,5,5],"arg_names":["fact_view_id","tags","next_rep","last_rep","easiness","reps","lapses"],"dataclass_transform_spec":null,"deprecated":null,"flags":["is_static","is_decorated"],"fullname":"anki.foreign_data.mnemosyne.MnemoCard.__mypy-replace","name":"__mypy-replace","type":{".class":"CallableType","arg_kinds":[5,5,5,5,5,5,5],"arg_names":["fact_view_id","tags","next_rep","last_rep","easiness","reps","lapses"],"arg_types":["builtins.str","builtins.str","builtins.int","builtins.int","builtins.float","builtins.int","builtins.int"],"bound_args":[],"def_extras":{},"fallback":"builtins.function","from_concatenate":false,"implicit":false,"imprecise_arg_kinds":false,"is_ellipsis_args":false,"name":"__mypy-replace of MnemoCard","ret_type":{".class":"NoneType"},"type_guard":null,"type_is":null,"unpack_kwargs":false,"variables":[]}},"is_overload":false,"var":{".class":"Var","flags":["is_staticmethod","is_ready"],"fullname":"anki.foreign_data.mnemosyne.MnemoCard.__mypy-replace","name":"__mypy-replace","type":{".class":"CallableType","arg_kinds":[5,5,5,5,5,5,5],"arg_names":["fact_view_id","tags","next_rep","last_rep","easiness","reps","lapses"],"arg_types":["builtins.str","builtins.str","builtins.int","builtins.int","builtins.float","builtins.int","builtins.int"],"bound_args":[],"def_extras":{},"fallback":"builtins.function","from_concatenate":false,"implicit":false,"imprecise_arg_kinds":false,"is_ellipsis_args":false,"name":"__mypy-replace of MnemoCard","ret_type":{".class":"NoneType"},"type_guard":null,"type_is":null,"unpack_kwargs":false,"variables":[]}}},"plugin_generated":true},"__replace__":{".class":"SymbolTableNode","kind":"Mdef","node":{".class":"FuncDef","abstract_status":0,"arg_kinds":[0,5,5,5,5,5,5,5],"arg_names":["self","fact_view_id","tags","next_rep","last_rep","easiness","reps","lapses"],"dataclass_transform_spec":null,"deprecated":null,"flags":[],"fullname":"anki.foreign_data.mnemosyne.MnemoCard.__replace__","name":"__replace__","type":{".class":"CallableType","arg_kinds":[0,5,5,5,5,5,5,5],"arg_names":["self","fact_view_id","tags","next_rep","last_rep","easiness","reps","lapses"],"arg_types":["anki.foreign_data.mnemosyne.MnemoCard","builtins.str","builtins.str","builtins.int","builtins.int","builtins.float","builtins.int","builtins.int"],"bound_args":[],"def_extras":{},"fallback":"builtins.function","from_concatenate":false,"implicit":false,"imprecise_arg_kinds":false,"is_ellipsis_args":false,"name":"__replace__ of MnemoCard","ret_type":"anki.foreign_data.mnemosyne.MnemoCard","type_guard":null,"type_is":null,"unpack_kwargs":false,"variables":[]}},"plugin_generated":true},"anki_interval":{".class":"SymbolTableNode","kind":"Mdef","node":{".class":"FuncDef","abstract_status":0,"arg_kinds":[0],"arg_names":["self"],"dataclass_transform_spec":null,"deprecated":null,"flags":[],"fullname":"anki.foreign_data.mnemosyne.MnemoCard.anki_interval","name":"anki_interval","type":{".class":"CallableType","arg_kinds":[0],"arg_names":["self"],"arg_types":["anki.foreign_data.mnemosyne.MnemoCard"],"bound_args":[],"def_extras":{"first_arg":"self"},"fallback":"builtins.function","from_concatenate":false,"implicit":false,"imprecise_arg_kinds":false,"is_ellipsis_args":false,"name":"anki_interval of MnemoCard","ret_type":"builtins.int","type_guard":null,"type_is":null,"unpack_kwargs":false,"variables":[]}}},"card_ord":{".class":"SymbolTableNode","kind":"Mdef","node":{".class":"FuncDef","abstract_status":0,"arg_kinds":[0],"arg_names":["self"],"dataclass_transform_spec":null,"deprecated":null,"flags":[],"fullname":"anki.foreign_data.mnemosyne.MnemoCard.card_ord","name":"card_ord","type":{".class":"CallableType","arg_kinds":[0],"arg_names":["self"],"arg_types":["anki.foreign_data.mnemosyne.MnemoCard"],"bound_args":[],"def_extras":{"first_arg":"self"},"fallback":"builtins.function","from_concatenate":false,"implicit":false,"imprecise_arg_kinds":false,"is_ellipsis_args":false,"name":"card_ord of MnemoCard","ret_type":"builtins.int","type_guard":null,"type_is":null,"unpack_kwargs":false,"variables":[]}}},"easiness":{".class":"SymbolTableNode","implicit":true,"kind":"Mdef","node":{".class":"Var","flags":["is_initialized_in_class","is_ready"],"fullname":"anki.foreign_data.mnemosyne.MnemoCard.easiness","name":"easiness","type":"builtins.float"}},"fact_view_id":{".class":"SymbolTableNode","implicit":true,"kind":"Mdef","node":{".class":"Var","flags":["is_initialized_in_class","is_ready"],"fullname":"anki.foreign_data.mnemosyne.MnemoCard.fact_view_id","name":"fact_view_id","type":"builtins.str"}},"foreign_card":{".class":"SymbolTableNode","kind":"Mdef","node":{".class":"FuncDef","abstract_status":0,"arg_kinds":[0],"arg_names":["self"],"dataclass_transform_spec":null,"deprecated":null,"flags":[],"fullname":"anki.foreign_data.mnemosyne.MnemoCard.foreign_card","name":"foreign_card","type":{".class":"CallableType","arg_kinds":[0],"arg_names":["self"],"arg_types":["anki.foreign_data.mnemosyne.MnemoCard"],"bound_args":[],"def_extras":{"first_arg":"self"},"fallback":"builtins.function","from_concatenate":false,"implicit":false,"imprecise_arg_kinds":false,"is_ellipsis_args":false,"name":"foreign_card of MnemoCard","ret_type":"anki.foreign_data.ForeignCard","type_guard":null,"type_is":null,"unpack_kwargs":false,"variables":[]}}},"is_new":{".class":"SymbolTableNode","kind":"Mdef","node":{".class":"FuncDef","abstract_status":0,"arg_kinds":[0],"arg_names":["self"],"dataclass_transform_spec":null,"deprecated":null,"flags":[],"fullname":"anki.foreign_data.mnemosyne.MnemoCard.is_new","name":"is_new","type":{".class":"CallableType","arg_kinds":[0],"arg_names":["self"],"arg_types":["anki.foreign_data.mnemosyne.MnemoCard"],"bound_args":[],"def_extras":{"first_arg":"self"},"fallback":"builtins.function","from_concatenate":false,"implicit":false,"imprecise_arg_kinds":false,"is_ellipsis_args":false,"name":"is_new of MnemoCard","ret_type":"builtins.bool","type_guard":null,"type_is":null,"unpack_kwargs":false,"variables":[]}}},"lapses":{".class":"SymbolTableNode","implicit":true,"kind":"Mdef","node":{".class":"Var","flags":["is_initialized_in_class","is_ready"],"fullname":"anki.foreign_data.mnemosyne.MnemoCard.lapses","name":"lapses","type":"builtins.int"}},"last_rep":{".class":"SymbolTableNode","implicit":true,"kind":"Mdef","node":{".class":"Var","flags":["is_initialized_in_class","is_ready"],"fullname":"anki.foreign_data.mnemosyne.MnemoCard.last_rep","name":"last_rep","type":"builtins.int"}},"next_rep":{".class":"SymbolTableNode","implicit":true,"kind":"Mdef","node":{".class":"Var","flags":["is_initialized_in_class","is_ready"],"fullname":"anki.foreign_data.mnemosyne.MnemoCard.next_rep","name":"next_rep","type":"builtins.int"}},"reps":{".class":"SymbolTableNode","implicit":true,"kind":"Mdef","node":{".class":"Var","flags":["is_initialized_in_class","is_ready"],"fullname":"anki.foreign_data.mnemosyne.MnemoCard.reps","name":"reps","type":"builtins.int"}},"tags":{".class":"SymbolTableNode","implicit":true,"kind":"Mdef","node":{".class":"Var","flags":["is_initialized_in_class","is_ready"],"fullname":"anki.foreign_data.mnemosyne.MnemoCard.tags","name":"tags","type":"builtins.str"}}},"self_type":{".class":"TypeVarType","default":{".class":"AnyType","missing_import_name":null,"source_any":null,"type_of_any":4},"fullname":"anki.foreign_data.mnemosyne.MnemoCard.Self","id":0,"name":"Self","namespace":"","upper_bound":"anki.foreign_data.mnemosyne.MnemoCard","values":[],"variance":0},"slots":null,"tuple_type":null,"type_vars":[],"typeddict_type":null}},"MnemoFact":{".class":"SymbolTableNode","kind":"Gdef","node":{".class":"TypeInfo","_promote":[],"abstract_attributes":[],"alt_promote":null,"bases":["builtins.object"],"dataclass_transform_spec":null,"declared_metaclass":null,"defn":{".class":"ClassDef","fullname":"anki.foreign_data.mnemosyne.MnemoFact","name":"MnemoFact","type_vars":[]},"deletable_attributes":[],"deprecated":null,"flags":[],"fullname":"anki.foreign_data.mnemosyne.MnemoFact","has_param_spec_type":false,"metaclass_type":null,"metadata":{"dataclass":{"attributes":[{"alias":null,"column":4,"has_default":false,"is_in_init":true,"is_init_var":false,"is_neither_frozen_nor_nonfrozen":false,"kw_only":false,"line":159,"name":"id","type":"builtins.int"},{"alias":null,"column":4,"has_default":true,"is_in_init":true,"is_init_var":false,"is_neither_frozen_nor_nonfrozen":false,"kw_only":false,"line":160,"name":"fields","type":{".class":"Instance","args":["builtins.str","builtins.str"],"extra_attrs":null,"type_ref":"builtins.dict"}},{"alias":null,"column":4,"has_default":true,"is_in_init":true,"is_init_var":false,"is_neither_frozen_nor_nonfrozen":false,"kw_only":false,"line":161,"name":"cards","type":{".class":"Instance","args":["anki.foreign_data.mnemosyne.MnemoCard"],"extra_attrs":null,"type_ref":"builtins.list"}}],"frozen":false},"dataclass_tag":{}},"module_name":"anki.foreign_data.mnemosyne","mro":["anki.foreign_data.mnemosyne.MnemoFact","builtins.object"],"names":{".class":"SymbolTable","__dataclass_fields__":{".class":"SymbolTableNode","kind":"Mdef","node":{".class":"Var","flags":["is_classvar","is_ready"],"fullname":"anki.foreign_data.mnemosyne.MnemoFact.__dataclass_fields__","name":"__dataclass_fields__","type":{".class":"Instance","args":["builtins.str",{".class":"Instance","args":[{".class":"AnyType","missing_import_name":null,"source_any":null,"type_of_any":2}],"extra_attrs":null,"type_ref":"dataclasses.Field"}],"extra_attrs":null,"type_ref":"builtins.dict"}},"plugin_generated":true},"__init__":{".class":"SymbolTableNode","kind":"Mdef","node":{".class":"FuncDef","abstract_status":0,"arg_kinds":[0,0,1,1],"arg_names":["self","id","fields","cards"],"dataclass_transform_spec":null,"deprecated":null,"flags":[],"fullname":"anki.foreign_data.mnemosyne.MnemoFact.__init__","name":"__init__","type":{".class":"CallableType","arg_kinds":[0,0,1,1],"arg_names":["self","id","fields","cards"],"arg_types":["anki.foreign_data.mnemosyne.MnemoFact","builtins.int",{".class":"Instance","args":["builtins.str","builtins.str"],"extra_attrs":null,"type_ref":"builtins.dict"},{".class":"Instance","args":["anki.foreign_data.mnemosyne.MnemoCard"],"extra_attrs":null,"type_ref":"builtins.list"}],"bound_args":[],"def_extras":{},"fallback":"builtins.function","from_concatenate":false,"implicit":false,"imprecise_arg_kinds":false,"is_ellipsis_args":false,"name":"__init__ of MnemoFact","ret_type":{".class":"NoneType"},"type_guard":null,"type_is":null,"unpack_kwargs":false,"variables":[]}},"plugin_generated":true},"__match_args__":{".class":"SymbolTableNode","kind":"Mdef","node":{".class":"Var","flags":["is_ready","allow_incompatible_override"],"fullname":"anki.foreign_data.mnemosyne.MnemoFact.__match_args__","name":"__match_args__","type":{".class":"TupleType","implicit":false,"items":[{".class":"LiteralType","fallback":"builtins.str","value":"id"},{".class":"LiteralType","fallback":"builtins.str","value":"fields"},{".class":"LiteralType","fallback":"builtins.str","value":"cards"}],"partial_fallback":{".class":"Instance","args":[{".class":"AnyType","missing_import_name":null,"source_any":null,"type_of_any":6}],"extra_attrs":null,"type_ref":"builtins.tuple"}}},"plugin_generated":true},"__mypy-replace":{".class":"SymbolTableNode","kind":"Mdef","node":{".class":"Decorator","func":{".class":"FuncDef","abstract_status":0,"arg_kinds":[5,5,5],"arg_names":["id","fields","cards"],"dataclass_transform_spec":null,"deprecated":null,"flags":["is_static","is_decorated"],"fullname":"anki.foreign_data.mnemosyne.MnemoFact.__mypy-replace","name":"__mypy-replace","type":{".class":"CallableType","arg_kinds":[5,5,5],"arg_names":["id","fields","cards"],"arg_types":["builtins.int",{".class":"Instance","args":["builtins.str","builtins.str"],"extra_attrs":null,"type_ref":"builtins.dict"},{".class":"Instance","args":["anki.foreign_data.mnemosyne.MnemoCard"],"extra_attrs":null,"type_ref":"builtins.list"}],"bound_args":[],"def_extras":{},"fallback":"builtins.function","from_concatenate":false,"implicit":false,"imprecise_arg_kinds":false,"is_ellipsis_args":false,"name":"__mypy-replace of MnemoFact","ret_type":{".class":"NoneType"},"type_guard":null,"type_is":null,"unpack_kwargs":false,"variables":[]}},"is_overload":false,"var":{".class":"Var","flags":["is_staticmethod","is_ready"],"fullname":"anki.foreign_data.mnemosyne.MnemoFact.__mypy-replace","name":"__mypy-replace","type":{".class":"CallableType","arg_kinds":[5,5,5],"arg_names":["id","fields","cards"],"arg_types":["builtins.int",{".class":"Instance","args":["builtins.str","builtins.str"],"extra_attrs":null,"type_ref":"builtins.dict"},{".class":"Instance","args":["anki.foreign_data.mnemosyne.MnemoCard"],"extra_attrs":null,"type_ref":"builtins.list"}],"bound_args":[],"def_extras":{},"fallback":"builtins.function","from_concatenate":false,"implicit":false,"imprecise_arg_kinds":false,"is_ellipsis_args":false,"name":"__mypy-replace of MnemoFact","ret_type":{".class":"NoneType"},"type_guard":null,"type_is":null,"unpack_kwargs":false,"variables":[]}}},"plugin_generated":true},"__replace__":{".class":"SymbolTableNode","kind":"Mdef","node":{".class":"FuncDef","abstract_status":0,"arg_kinds":[0,5,5,5],"arg_names":["self","id","fields","cards"],"dataclass_transform_spec":null,"deprecated":null,"flags":[],"fullname":"anki.foreign_data.mnemosyne.MnemoFact.__replace__","name":"__replace__","type":{".class":"CallableType","arg_kinds":[0,5,5,5],"arg_names":["self","id","fields","cards"],"arg_types":["anki.foreign_data.mnemosyne.MnemoFact","builtins.int",{".class":"Instance","args":["builtins.str","builtins.str"],"extra_attrs":null,"type_ref":"builtins.dict"},{".class":"Instance","args":["anki.foreign_data.mnemosyne.MnemoCard"],"extra_attrs":null,"type_ref":"builtins.list"}],"bound_args":[],"def_extras":{},"fallback":"builtins.function","from_concatenate":false,"implicit":false,"imprecise_arg_kinds":false,"is_ellipsis_args":false,"name":"__replace__ of MnemoFact","ret_type":"anki.foreign_data.mnemosyne.MnemoFact","type_guard":null,"type_is":null,"unpack_kwargs":false,"variables":[]}},"plugin_generated":true},"anki_fields":{".class":"SymbolTableNode","kind":"Mdef","node":{".class":"FuncDef","abstract_status":0,"arg_kinds":[0,0],"arg_names":["self","fact_view"],"dataclass_transform_spec":null,"deprecated":null,"flags":[],"fullname":"anki.foreign_data.mnemosyne.MnemoFact.anki_fields","name":"anki_fields","type":{".class":"CallableType","arg_kinds":[0,0],"arg_names":["self","fact_view"],"arg_types":["anki.foreign_data.mnemosyne.MnemoFact",{".class":"TypeType","item":"anki.foreign_data.mnemosyne.MnemoFactView"}],"bound_args":[],"def_extras":{"first_arg":"self"},"fallback":"builtins.function","from_concatenate":false,"implicit":false,"imprecise_arg_kinds":false,"is_ellipsis_args":false,"name":"anki_fields of MnemoFact","ret_type":{".class":"Instance","args":["builtins.str"],"extra_attrs":null,"type_ref":"builtins.list"},"type_guard":null,"type_is":null,"unpack_kwargs":false,"variables":[]}}},"anki_tags":{".class":"SymbolTableNode","kind":"Mdef","node":{".class":"FuncDef","abstract_status":0,"arg_kinds":[0],"arg_names":["self"],"dataclass_transform_spec":null,"deprecated":null,"flags":[],"fullname":"anki.foreign_data.mnemosyne.MnemoFact.anki_tags","name":"anki_tags","type":{".class":"CallableType","arg_kinds":[0],"arg_names":["self"],"arg_types":["anki.foreign_data.mnemosyne.MnemoFact"],"bound_args":[],"def_extras":{"first_arg":"self"},"fallback":"builtins.function","from_concatenate":false,"implicit":false,"imprecise_arg_kinds":false,"is_ellipsis_args":false,"name":"anki_tags of MnemoFact","ret_type":{".class":"Instance","args":["builtins.str"],"extra_attrs":null,"type_ref":"builtins.list"},"type_guard":null,"type_is":null,"unpack_kwargs":false,"variables":[]}}},"cards":{".class":"SymbolTableNode","kind":"Mdef","node":{".class":"Var","flags":["is_initialized_in_class","is_ready","has_explicit_value"],"fullname":"anki.foreign_data.mnemosyne.MnemoFact.cards","name":"cards","type":{".class":"Instance","args":["anki.foreign_data.mnemosyne.MnemoCard"],"extra_attrs":null,"type_ref":"builtins.list"}}},"fact_view":{".class":"SymbolTableNode","kind":"Mdef","node":{".class":"FuncDef","abstract_status":0,"arg_kinds":[0],"arg_names":["self"],"dataclass_transform_spec":null,"deprecated":null,"flags":[],"fullname":"anki.foreign_data.mnemosyne.MnemoFact.fact_view","name":"fact_view","type":{".class":"CallableType","arg_kinds":[0],"arg_names":["self"],"arg_types":["anki.foreign_data.mnemosyne.MnemoFact"],"bound_args":[],"def_extras":{"first_arg":"self"},"fallback":"builtins.function","from_concatenate":false,"implicit":false,"imprecise_arg_kinds":false,"is_ellipsis_args":false,"name":"fact_view of MnemoFact","ret_type":{".class":"TypeType","item":"anki.foreign_data.mnemosyne.MnemoFactView"},"type_guard":null,"type_is":null,"unpack_kwargs":false,"variables":[]}}},"fields":{".class":"SymbolTableNode","kind":"Mdef","node":{".class":"Var","flags":["is_initialized_in_class","is_ready","has_explicit_value"],"fullname":"anki.foreign_data.mnemosyne.MnemoFact.fields","name":"fields","type":{".class":"Instance","args":["builtins.str","builtins.str"],"extra_attrs":null,"type_ref":"builtins.dict"}}},"foreign_cards":{".class":"SymbolTableNode","kind":"Mdef","node":{".class":"FuncDef","abstract_status":0,"arg_kinds":[0],"arg_names":["self"],"dataclass_transform_spec":null,"deprecated":null,"flags":[],"fullname":"anki.foreign_data.mnemosyne.MnemoFact.foreign_cards","name":"foreign_cards","type":{".class":"CallableType","arg_kinds":[0],"arg_names":["self"],"arg_types":["anki.foreign_data.mnemosyne.MnemoFact"],"bound_args":[],"def_extras":{"first_arg":"self"},"fallback":"builtins.function","from_concatenate":false,"implicit":false,"imprecise_arg_kinds":false,"is_ellipsis_args":false,"name":"foreign_cards of MnemoFact","ret_type":{".class":"Instance","args":["anki.foreign_data.ForeignCard"],"extra_attrs":null,"type_ref":"builtins.list"},"type_guard":null,"type_is":null,"unpack_kwargs":false,"variables":[]}}},"foreign_note":{".class":"SymbolTableNode","kind":"Mdef","node":{".class":"FuncDef","abstract_status":0,"arg_kinds":[0,0],"arg_names":["self","used_fact_views"],"dataclass_transform_spec":null,"deprecated":null,"flags":[],"fullname":"anki.foreign_data.mnemosyne.MnemoFact.foreign_note","name":"foreign_note","type":{".class":"CallableType","arg_kinds":[0,0],"arg_names":["self","used_fact_views"],"arg_types":["anki.foreign_data.mnemosyne.MnemoFact",{".class":"Instance","args":[{".class":"TypeType","item":"anki.foreign_data.mnemosyne.MnemoFactView"},"builtins.bool"],"extra_attrs":null,"type_ref":"builtins.dict"}],"bound_args":[],"def_extras":{"first_arg":"self"},"fallback":"builtins.function","from_concatenate":false,"implicit":false,"imprecise_arg_kinds":false,"is_ellipsis_args":false,"name":"foreign_note of MnemoFact","ret_type":"anki.foreign_data.ForeignNote","type_guard":null,"type_is":null,"unpack_kwargs":false,"variables":[]}}},"id":{".class":"SymbolTableNode","implicit":true,"kind":"Mdef","node":{".class":"Var","flags":["is_initialized_in_class","is_ready"],"fullname":"anki.foreign_data.mnemosyne.MnemoFact.id","name":"id","type":"builtins.int"}}},"self_type":{".class":"TypeVarType","default":{".class":"AnyType","missing_import_name":null,"source_any":null,"type_of_any":4},"fullname":"anki.foreign_data.mnemosyne.MnemoFact.Self","id":0,"name":"Self","namespace":"","upper_bound":"anki.foreign_data.mnemosyne.MnemoFact","values":[],"variance":0},"slots":null,"tuple_type":null,"type_vars":[],"typeddict_type":null}},"MnemoFactView":{".class":"SymbolTableNode","kind":"Gdef","node":{".class":"TypeInfo","_promote":[],"abstract_attributes":[["foreign_notetype",1]],"alt_promote":null,"bases":["abc.ABC"],"dataclass_transform_spec":null,"declared_metaclass":null,"defn":{".class":"ClassDef","fullname":"anki.foreign_data.mnemosyne.MnemoFactView","name":"MnemoFactView","type_vars":[]},"deletable_attributes":[],"deprecated":null,"flags":["is_abstract"],"fullname":"anki.foreign_data.mnemosyne.MnemoFactView","has_param_spec_type":false,"metaclass_type":"abc.ABCMeta","metadata":{},"module_name":"anki.foreign_data.mnemosyne","mro":["anki.foreign_data.mnemosyne.MnemoFactView","abc.ABC","builtins.object"],"names":{".class":"SymbolTable","field_keys":{".class":"SymbolTableNode","kind":"Mdef","node":{".class":"Var","flags":["is_initialized_in_class","is_ready"],"fullname":"anki.foreign_data.mnemosyne.MnemoFactView.field_keys","name":"field_keys","type":{".class":"Instance","args":["builtins.str"],"extra_attrs":null,"type_ref":"builtins.tuple"}}},"foreign_notetype":{".class":"SymbolTableNode","kind":"Mdef","node":{".class":"Decorator","func":{".class":"FuncDef","abstract_status":1,"arg_kinds":[0],"arg_names":["cls"],"dataclass_transform_spec":null,"deprecated":null,"flags":["is_class","is_decorated","is_trivial_body"],"fullname":"anki.foreign_data.mnemosyne.MnemoFactView.foreign_notetype","name":"foreign_notetype","type":{".class":"CallableType","arg_kinds":[0],"arg_names":["cls"],"arg_types":[{".class":"TypeType","item":"anki.foreign_data.mnemosyne.MnemoFactView"}],"bound_args":[],"def_extras":{"first_arg":"cls"},"fallback":"builtins.function","from_concatenate":false,"implicit":false,"imprecise_arg_kinds":false,"is_ellipsis_args":false,"name":"foreign_notetype of MnemoFactView","ret_type":"anki.foreign_data.ForeignNotetype","type_guard":null,"type_is":null,"unpack_kwargs":false,"variables":[]}},"is_overload":false,"var":{".class":"Var","flags":["is_initialized_in_class","is_classmethod","is_ready","is_inferred"],"fullname":"anki.foreign_data.mnemosyne.MnemoFactView.foreign_notetype","name":"foreign_notetype","type":{".class":"CallableType","arg_kinds":[0],"arg_names":["cls"],"arg_types":[{".class":"TypeType","item":"anki.foreign_data.mnemosyne.MnemoFactView"}],"bound_args":[],"def_extras":{"first_arg":"cls"},"fallback":"builtins.function","from_concatenate":false,"implicit":false,"imprecise_arg_kinds":false,"is_ellipsis_args":false,"name":"foreign_notetype of MnemoFactView","ret_type":"anki.foreign_data.ForeignNotetype","type_guard":null,"type_is":null,"unpack_kwargs":false,"variables":[]}}}},"notetype":{".class":"SymbolTableNode","kind":"Mdef","node":{".class":"Var","flags":["is_initialized_in_class","is_ready"],"fullname":"anki.foreign_data.mnemosyne.MnemoFactView.notetype","name":"notetype","type":"builtins.str"}}},"self_type":{".class":"TypeVarType","default":{".class":"AnyType","missing_import_name":null,"source_any":null,"type_of_any":4},"fullname":"anki.foreign_data.mnemosyne.MnemoFactView.Self","id":0,"name":"Self","namespace":"","upper_bound":"anki.foreign_data.mnemosyne.MnemoFactView","values":[],"variance":0},"slots":null,"tuple_type":null,"type_vars":[],"typeddict_type":null}},"Vocabulary":{".class":"SymbolTableNode","kind":"Gdef","node":{".class":"TypeInfo","_promote":[],"abstract_attributes":[],"alt_promote":null,"bases":["anki.foreign_data.mnemosyne.MnemoFactView"],"dataclass_transform_spec":null,"declared_metaclass":null,"defn":{".class":"ClassDef","fullname":"anki.foreign_data.mnemosyne.Vocabulary","name":"Vocabulary","type_vars":[]},"deletable_attributes":[],"deprecated":null,"flags":[],"fullname":"anki.foreign_data.mnemosyne.Vocabulary","has_param_spec_type":false,"metaclass_type":"abc.ABCMeta","metadata":{},"module_name":"anki.foreign_data.mnemosyne","mro":["anki.foreign_data.mnemosyne.Vocabulary","anki.foreign_data.mnemosyne.MnemoFactView","abc.ABC","builtins.object"],"names":{".class":"SymbolTable","_production_card_type":{".class":"SymbolTableNode","kind":"Mdef","node":{".class":"Decorator","func":{".class":"FuncDef","abstract_status":0,"arg_kinds":[],"arg_names":[],"dataclass_transform_spec":null,"deprecated":null,"flags":["is_static","is_decorated"],"fullname":"anki.foreign_data.mnemosyne.Vocabulary._production_card_type","name":"_production_card_type","type":{".class":"CallableType","arg_kinds":[],"arg_names":[],"arg_types":[],"bound_args":[],"def_extras":{"first_arg":null},"fallback":"builtins.function","from_concatenate":false,"implicit":false,"imprecise_arg_kinds":false,"is_ellipsis_args":false,"name":"_production_card_type of Vocabulary","ret_type":"anki.foreign_data.ForeignCardType","type_guard":null,"type_is":null,"unpack_kwargs":false,"variables":[]}},"is_overload":false,"var":{".class":"Var","flags":["is_initialized_in_class","is_staticmethod","is_ready","is_inferred"],"fullname":"anki.foreign_data.mnemosyne.Vocabulary._production_card_type","name":"_production_card_type","type":{".class":"CallableType","arg_kinds":[],"arg_names":[],"arg_types":[],"bound_args":[],"def_extras":{"first_arg":null},"fallback":"builtins.function","from_concatenate":false,"implicit":false,"imprecise_arg_kinds":false,"is_ellipsis_args":false,"name":"_production_card_type of Vocabulary","ret_type":"anki.foreign_data.ForeignCardType","type_guard":null,"type_is":null,"unpack_kwargs":false,"variables":[]}}}},"_recognition_card_type":{".class":"SymbolTableNode","kind":"Mdef","node":{".class":"Decorator","func":{".class":"FuncDef","abstract_status":0,"arg_kinds":[],"arg_names":[],"dataclass_transform_spec":null,"deprecated":null,"flags":["is_static","is_decorated"],"fullname":"anki.foreign_data.mnemosyne.Vocabulary._recognition_card_type","name":"_recognition_card_type","type":{".class":"CallableType","arg_kinds":[],"arg_names":[],"arg_types":[],"bound_args":[],"def_extras":{"first_arg":null},"fallback":"builtins.function","from_concatenate":false,"implicit":false,"imprecise_arg_kinds":false,"is_ellipsis_args":false,"name":"_recognition_card_type of Vocabulary","ret_type":"anki.foreign_data.ForeignCardType","type_guard":null,"type_is":null,"unpack_kwargs":false,"variables":[]}},"is_overload":false,"var":{".class":"Var","flags":["is_initialized_in_class","is_staticmethod","is_ready","is_inferred"],"fullname":"anki.foreign_data.mnemosyne.Vocabulary._recognition_card_type","name":"_recognition_card_type","type":{".class":"CallableType","arg_kinds":[],"arg_names":[],"arg_types":[],"bound_args":[],"def_extras":{"first_arg":null},"fallback":"builtins.function","from_concatenate":false,"implicit":false,"imprecise_arg_kinds":false,"is_ellipsis_args":false,"name":"_recognition_card_type of Vocabulary","ret_type":"anki.foreign_data.ForeignCardType","type_guard":null,"type_is":null,"unpack_kwargs":false,"variables":[]}}}},"field_keys":{".class":"SymbolTableNode","kind":"Mdef","node":{".class":"Var","flags":["is_initialized_in_class","is_inferred","has_explicit_value"],"fullname":"anki.foreign_data.mnemosyne.Vocabulary.field_keys","name":"field_keys","type":{".class":"TupleType","implicit":false,"items":["builtins.str","builtins.str","builtins.str","builtins.str"],"partial_fallback":{".class":"Instance","args":[{".class":"AnyType","missing_import_name":null,"source_any":null,"type_of_any":6}],"extra_attrs":null,"type_ref":"builtins.tuple"}}}},"foreign_notetype":{".class":"SymbolTableNode","kind":"Mdef","node":{".class":"Decorator","func":{".class":"FuncDef","abstract_status":0,"arg_kinds":[0],"arg_names":["cls"],"dataclass_transform_spec":null,"deprecated":null,"flags":["is_class","is_decorated"],"fullname":"anki.foreign_data.mnemosyne.Vocabulary.foreign_notetype","name":"foreign_notetype","type":{".class":"CallableType","arg_kinds":[0],"arg_names":["cls"],"arg_types":[{".class":"TypeType","item":"anki.foreign_data.mnemosyne.Vocabulary"}],"bound_args":[],"def_extras":{"first_arg":"cls"},"fallback":"builtins.function","from_concatenate":false,"implicit":false,"imprecise_arg_kinds":false,"is_ellipsis_args":false,"name":"foreign_notetype of Vocabulary","ret_type":"anki.foreign_data.ForeignNotetype","type_guard":null,"type_is":null,"unpack_kwargs":false,"variables":[]}},"is_overload":false,"var":{".class":"Var","flags":["is_initialized_in_class","is_classmethod","is_ready","is_inferred"],"fullname":"anki.foreign_data.mnemosyne.Vocabulary.foreign_notetype","name":"foreign_notetype","type":{".class":"CallableType","arg_kinds":[0],"arg_names":["cls"],"arg_types":[{".class":"TypeType","item":"anki.foreign_data.mnemosyne.Vocabulary"}],"bound_args":[],"def_extras":{"first_arg":"cls"},"fallback":"builtins.function","from_concatenate":false,"implicit":false,"imprecise_arg_kinds":false,"is_ellipsis_args":false,"name":"foreign_notetype of Vocabulary","ret_type":"anki.foreign_data.ForeignNotetype","type_guard":null,"type_is":null,"unpack_kwargs":false,"variables":[]}}}},"notetype":{".class":"SymbolTableNode","kind":"Mdef","node":{".class":"Var","flags":["is_initialized_in_class","is_inferred","has_explicit_value"],"fullname":"anki.foreign_data.mnemosyne.Vocabulary.notetype","name":"notetype","type":"builtins.str"}}},"self_type":{".class":"TypeVarType","default":{".class":"AnyType","missing_import_name":null,"source_any":null,"type_of_any":4},"fullname":"anki.foreign_data.mnemosyne.Vocabulary.Self","id":0,"name":"Self","namespace":"","upper_bound":"anki.foreign_data.mnemosyne.Vocabulary","values":[],"variance":0},"slots":null,"tuple_type":null,"type_vars":[],"typeddict_type":null}},"__annotations__":{".class":"SymbolTableNode","kind":"Gdef","node":{".class":"Var","flags":["is_ready"],"fullname":"anki.foreign_data.mnemosyne.__annotations__","name":"__annotations__","type":{".class":"Instance","args":["builtins.str",{".class":"AnyType","missing_import_name":null,"source_any":null,"type_of_any":6}],"extra_attrs":null,"type_ref":"builtins.dict"}}},"__doc__":{".class":"SymbolTableNode","kind":"Gdef","node":{".class":"Var","flags":["is_ready"],"fullname":"anki.foreign_data.mnemosyne.__doc__","name":"__doc__","type":"builtins.str"}},"__file__":{".class":"SymbolTableNode","kind":"Gdef","node":{".class":"Var","flags":["is_ready"],"fullname":"anki.foreign_data.mnemosyne.__file__","name":"__file__","type":"builtins.str"}},"__name__":{".class":"SymbolTableNode","kind":"Gdef","node":{".class":"Var","flags":["is_ready"],"fullname":"anki.foreign_data.mnemosyne.__name__","name":"__name__","type":"builtins.str"}},"__package__":{".class":"SymbolTableNode","kind":"Gdef","node":{".class":"Var","flags":["is_ready"],"fullname":"anki.foreign_data.mnemosyne.__package__","name":"__package__","type":"builtins.str"}},"__spec__":{".class":"SymbolTableNode","kind":"Gdef","node":{".class":"Var","flags":["is_ready"],"fullname":"anki.foreign_data.mnemosyne.__spec__","name":"__spec__","type":"_frozen_importlib.ModuleSpec"}},"abstractmethod":{".class":"SymbolTableNode","cross_ref":"abc.abstractmethod","kind":"Gdef"},"dataclass":{".class":"SymbolTableNode","cross_ref":"dataclasses.dataclass","kind":"Gdef"},"field":{".class":"SymbolTableNode","cross_ref":"dataclasses.field","kind":"Gdef"},"gather_cards_into_facts":{".class":"SymbolTableNode","kind":"Gdef","node":{".class":"FuncDef","abstract_status":0,"arg_kinds":[0,0],"arg_names":["db","facts"],"dataclass_transform_spec":null,"deprecated":null,"flags":[],"fullname":"anki.foreign_data.mnemosyne.gather_cards_into_facts","name":"gather_cards_into_facts","type":{".class":"CallableType","arg_kinds":[0,0],"arg_names":["db","facts"],"arg_types":["anki.db.DB",{".class":"Instance","args":["builtins.int","anki.foreign_data.mnemosyne.MnemoFact"],"extra_attrs":null,"type_ref":"builtins.dict"}],"bound_args":[],"def_extras":{"first_arg":null},"fallback":"builtins.function","from_concatenate":false,"implicit":false,"imprecise_arg_kinds":false,"is_ellipsis_args":false,"name":"gather_cards_into_facts","ret_type":{".class":"NoneType"},"type_guard":null,"type_is":null,"unpack_kwargs":false,"variables":[]}}},"gather_data":{".class":"SymbolTableNode","kind":"Gdef","node":{".class":"FuncDef","abstract_status":0,"arg_kinds":[0,0],"arg_names":["db","deck_id"],"dataclass_transform_spec":null,"deprecated":null,"flags":[],"fullname":"anki.foreign_data.mnemosyne.gather_data","name":"gather_data","type":{".class":"CallableType","arg_kinds":[0,0],"arg_names":["db","deck_id"],"arg_types":["anki.db.DB","anki.decks.DeckId"],"bound_args":[],"def_extras":{"first_arg":null},"fallback":"builtins.function","from_concatenate":false,"implicit":false,"imprecise_arg_kinds":false,"is_ellipsis_args":false,"name":"gather_data","ret_type":"anki.foreign_data.ForeignData","type_guard":null,"type_is":null,"unpack_kwargs":false,"variables":[]}}},"gather_facts":{".class":"SymbolTableNode","kind":"Gdef","node":{".class":"FuncDef","abstract_status":0,"arg_kinds":[0],"arg_names":["db"],"dataclass_transform_spec":null,"deprecated":null,"flags":[],"fullname":"anki.foreign_data.mnemosyne.gather_facts","name":"gather_facts","type":{".class":"CallableType","arg_kinds":[0],"arg_names":["db"],"arg_types":["anki.db.DB"],"bound_args":[],"def_extras":{"first_arg":null},"fallback":"builtins.function","from_concatenate":false,"implicit":false,"imprecise_arg_kinds":false,"is_ellipsis_args":false,"name":"gather_facts","ret_type":{".class":"Instance","args":["builtins.int","anki.foreign_data.mnemosyne.MnemoFact"],"extra_attrs":null,"type_ref":"builtins.dict"},"type_guard":null,"type_is":null,"unpack_kwargs":false,"variables":[]}}},"munge_field":{".class":"SymbolTableNode","kind":"Gdef","node":{".class":"FuncDef","abstract_status":0,"arg_kinds":[0],"arg_names":["field"],"dataclass_transform_spec":null,"deprecated":null,"flags":[],"fullname":"anki.foreign_data.mnemosyne.munge_field","name":"munge_field","type":{".class":"CallableType","arg_kinds":[0],"arg_names":["field"],"arg_types":["builtins.str"],"bound_args":[],"def_extras":{"first_arg":null},"fallback":"builtins.function","from_concatenate":false,"implicit":false,"imprecise_arg_kinds":false,"is_ellipsis_args":false,"name":"munge_field","ret_type":"builtins.str","type_guard":null,"type_is":null,"unpack_kwargs":false,"variables":[]}}},"open_mnemosyne_db":{".class":"SymbolTableNode","kind":"Gdef","node":{".class":"FuncDef","abstract_status":0,"arg_kinds":[0],"arg_names":["db_path"],"dataclass_transform_spec":null,"deprecated":null,"flags":[],"fullname":"anki.foreign_data.mnemosyne.open_mnemosyne_db","name":"open_mnemosyne_db","type":{".class":"CallableType","arg_kinds":[0],"arg_names":["db_path"],"arg_types":["builtins.str"],"bound_args":[],"def_extras":{"first_arg":null},"fallback":"builtins.function","from_concatenate":false,"implicit":false,"imprecise_arg_kinds":false,"is_ellipsis_args":false,"name":"open_mnemosyne_db","ret_type":"anki.db.DB","type_guard":null,"type_is":null,"unpack_kwargs":false,"variables":[]}}},"re":{".class":"SymbolTableNode","cross_ref":"re","kind":"Gdef"},"serialize":{".class":"SymbolTableNode","kind":"Gdef","node":{".class":"FuncDef","abstract_status":0,"arg_kinds":[0,0],"arg_names":["db_path","deck_id"],"dataclass_transform_spec":null,"deprecated":null,"flags":[],"fullname":"anki.foreign_data.mnemosyne.serialize","name":"serialize","type":{".class":"CallableType","arg_kinds":[0,0],"arg_names":["db_path","deck_id"],"arg_types":["builtins.str","anki.decks.DeckId"],"bound_args":[],"def_extras":{"first_arg":null},"fallback":"builtins.function","from_concatenate":false,"implicit":false,"imprecise_arg_kinds":false,"is_ellipsis_args":false,"name":"serialize","ret_type":"builtins.str","type_guard":null,"type_is":null,"unpack_kwargs":false,"variables":[]}}}},"path":"/Users/likai/Github/Tools/Anki-addon-dev-toolkit/.venv/lib/python3.13/site-packages/anki/foreign_data/mnemosyne.py"}